.gitignore
LICENSE
README.md
commond.txt
setup.py
pydnsfeature/__init__.py
pydnsfeature.egg-info/PKG-INFO
pydnsfeature.egg-info/SOURCES.txt
pydnsfeature.egg-info/dependency_links.txt
pydnsfeature.egg-info/requires.txt
pydnsfeature.egg-info/top_level.txt